{"bait": {"12711": {"name": "Brute Leech", "misses": 190, "total": 808}, "12757": {"name": "Hedgemole Cricket", "misses": 1219, "total": 1744}, "28634": {"name": "Metal Spinner", "misses": 0, "total": 430}, "12705": {"name": "Purse Web Spider", "misses": 943, "total": 4441}, "12704": {"name": "Stonefly Nymph", "misses": 168, "total": 578}, "29717": {"name": "Versatile Lure", "misses": 0, "total": 301}}, "fish": {"12757": {"name": "Hedgemole Cricket", "tug": "1"}, "12818": {"name": "Yalm Lobster", "tug": "2"}, "17585": {"name": "The Speaker", "tug": "3"}, "12747": {"name": "Scholar Sculpin", "tug": "2"}, "17562": {"name": "Thavnairian Leaf", "tug": "2"}, "12780": {"name": "Sweetfish", "tug": "2"}, "12830": {"name": "Loosetongue", "tug": "3"}, "14220": {"name": "Armored Catfish", "tug": "2"}, "17590": {"name": "Armor Fish", "tug": "3"}, "12756": {"name": "Shipworm", "tug": "1"}}, "rates": {"12711": {"12830": {"catches": "111", "naive": 3, "uniform": 3, "kde": 3, "bitetime_low": 14.5, "bitetime_high": 31.0}, "12757": {"catches": "55", "naive": 64, "uniform": 64, "kde": 64, "bitetime_low": 6.0, "bitetime_high": 15.0}, "14220": {"catches": "89", "naive": 24, "uniform": 28, "kde": 30, "bitetime_low": 15.0, "bitetime_high": 26.0}, "12747": {"catches": "61", "naive": 17, "uniform": 26, "kde": 33, "bitetime_low": 13.0, "bitetime_high": 24.0}, "12780": {"catches": "127", "naive": 35, "uniform": 29, "kde": 31, "bitetime_low": 11.0, "bitetime_high": 16.5}, "12818": {"catches": "175", "naive": 48, "uniform": 36, "kde": 29, "bitetime_low": 17.0, "bitetime_high": 29.0}}, "12757": {"17590": {"catches": "46", "naive": 70, "uniform": 86, "kde": 89, "bitetime_low": 20.0, "bitetime_high": 31.5}, "17585": {"catches": "55", "naive": 84, "uniform": 64, "kde": 65, "bitetime_low": 15.5, "bitetime_high": 26.0}, "12747": {"catches": "272", "naive": 683, "uniform": 406, "kde": 691, "bitetime_low": 10.5, "bitetime_high": 18.0}, "12818": {"catches": "152", "naive": 382, "uniform": 631, "kde": 374, "bitetime_low": 17.0, "bitetime_high": 30.0}}, "28634": {"12757": {"catches": "49", "naive": 0, "uniform": 0, "kde": 0, "bitetime_low": 7.0, "bitetime_high": 13.5}, "12747": {"catches": "77", "naive": 0, "uniform": 0, "kde": 0, "bitetime_low": 10.0, "bitetime_high": 18.0}, "12780": {"catches": "49", "naive": 0, "uniform": 0, "kde": 0, "bitetime_low": 11.0, "bitetime_high": 16.5}, "17562": {"catches": "255", "naive": 0, "uniform": 0, "kde": 0, "bitetime_low": 6.5, "bitetime_high": 13.5}}, "12705": {"12757": {"catches": "2946", "naive": 132, "uniform": 132, "kde": 132, "bitetime_low": 6.0, "bitetime_high": 13.0}, "12747": {"catches": "552", "naive": 811, "uniform": 811, "kde": 811, "bitetime_low": 10.0, "bitetime_high": 22.0}}, "12704": {"12757": {"catches": "309", "naive": 20, "uniform": 20, "kde": 20, "bitetime_low": 6.0, "bitetime_high": 14.5}, "17562": {"catches": "101", "naive": 148, "uniform": 148, "kde": 148, "bitetime_low": 9.5, "bitetime_high": 22.5}}, "29717": {"12757": {"catches": "48", "naive": 0, "uniform": 0, "kde": 0, "bitetime_low": 8.5, "bitetime_high": 11.5}, "12756": {"catches": "98", "naive": 0, "uniform": 0, "kde": 0, "bitetime_low": 14.5, "bitetime_high": 27.0}, "12747": {"catches": "44", "naive": 0, "uniform": 0, "kde": 0, "bitetime_low": 13.5, "bitetime_high": 20.5}, "17562": {"catches": "111", "naive": 0, "uniform": 0, "kde": 0, "bitetime_low": 10.0, "bitetime_high": 16.0}}}}