{"bait": {"20619": {"name": "Suspending Minnow", "misses": 901, "total": 1472}, "29717": {"name": "Versatile Lure", "misses": 0, "total": 95}}, "fish": {"20046": {"name": "River Barramundi", "tug": "2"}, "20123": {"name": "Doman Trout", "tug": "2"}, "20111": {"name": "Doman Crayfish", "tug": "1"}, "24886": {"name": "Glarramundi", "tug": "3"}}, "rates": {"20619": {"24886": {"catches": "61", "naive": 29, "uniform": 29, "kde": 29, "bitetime_low": 18.5, "bitetime_high": 35.0}, "20111": {"catches": "158", "naive": 374, "uniform": 374, "kde": 374, "bitetime_low": 6.0, "bitetime_high": 15.5}, "20123": {"catches": "161", "naive": 228, "uniform": 215, "kde": 268, "bitetime_low": 9.5, "bitetime_high": 16.5}, "20046": {"catches": "191", "naive": 270, "uniform": 263, "kde": 230, "bitetime_low": 12.5, "bitetime_high": 22.5}}, "29717": {"20123": {"catches": "47", "naive": 0, "uniform": 0, "kde": 0, "bitetime_low": 12.0, "bitetime_high": 18.0}, "20046": {"catches": "48", "naive": 0, "uniform": 0, "kde": 0, "bitetime_low": 14.0, "bitetime_high": 24.5}}}}