{"bait": {"27589": {"name": "Baitbugs", "misses": 56, "total": 161}, "27582": {"name": "Fruit Worm", "misses": 3364, "total": 4451}, "29717": {"name": "Versatile Lure", "misses": 0, "total": 119}}, "fish": {"27417": {"name": "Crystal Knife", "tug": "2"}, "27411": {"name": "Laxan Carp", "tug": "2"}, "27415": {"name": "Sinspitter", "tug": "1"}, "27416": {"name": "Wandering Catfish", "tug": "1"}, "30432": {"name": "The Sinsteeped", "tug": "3"}}, "rates": {"27589": {"27417": {"catches": "56", "naive": 28, "uniform": 22, "kde": 29, "bitetime_low": 11.5, "bitetime_high": 18.0}, "27411": {"catches": "49", "naive": 24, "uniform": 30, "kde": 23, "bitetime_low": 14.5, "bitetime_high": 24.5}}, "27582": {"30432": {"catches": "53", "naive": 6, "uniform": 6, "kde": 6, "bitetime_low": 10.5, "bitetime_high": 19.5}, "27415": {"catches": "190", "naive": 628, "uniform": 500, "kde": 495, "bitetime_low": 14.5, "bitetime_high": 28.5}, "27416": {"catches": "90", "naive": 297, "uniform": 425, "kde": 430, "bitetime_low": 17.5, "bitetime_high": 31.0}, "27417": {"catches": "373", "naive": 1204, "uniform": 1129, "kde": 1357, "bitetime_low": 5.5, "bitetime_high": 13.5}, "27411": {"catches": "381", "naive": 1229, "uniform": 1304, "kde": 1076, "bitetime_low": 9.0, "bitetime_high": 19.0}}, "29717": {"27417": {"catches": "65", "naive": 0, "uniform": 0, "kde": 0, "bitetime_low": 8.0, "bitetime_high": 16.0}, "27411": {"catches": "54", "naive": 0, "uniform": 0, "kde": 0, "bitetime_low": 8.0, "bitetime_high": 22.5}}}}