{"bait": {"36412": {"name": "Astacus Aetherius", "misses": 0, "total": 389}, "36589": {"name": "Leech", "misses": 240, "total": 701}, "36591": {"name": "Mayfly", "misses": 0, "total": 319}, "29717": {"name": "Versatile Lure", "misses": 0, "total": 121}}, "fish": {"36398": {"name": "Xenocypris", "tug": "2"}, "36412": {"name": "Astacus Aetherius", "tug": "2"}, "36414": {"name": "Labyrinthos Tilapia", "tug": "2"}, "36397": {"name": "Butterfly Fry", "tug": "1"}}, "rates": {"36412": {"36412": {"catches": "191", "naive": 0, "uniform": 0, "kde": 0, "bitetime_low": 9.5, "bitetime_high": 19.5}, "36414": {"catches": "198", "naive": 0, "uniform": 0, "kde": 0, "bitetime_low": 12.5, "bitetime_high": 25.5}}, "36589": {"36397": {"catches": "195", "naive": 202, "uniform": 202, "kde": 202, "bitetime_low": 4.5, "bitetime_high": 15.0}, "36412": {"catches": "83", "naive": 12, "uniform": 0, "kde": 4, "bitetime_low": 15.0, "bitetime_high": 25.5}, "36398": {"catches": "183", "naive": 26, "uniform": 36, "kde": 34, "bitetime_low": 6.5, "bitetime_high": 13.5}}, "36591": {"36412": {"catches": "232", "naive": 0, "uniform": 0, "kde": 0, "bitetime_low": 9.0, "bitetime_high": 19.5}, "36398": {"catches": "87", "naive": 0, "uniform": 0, "kde": 0, "bitetime_low": 9.5, "bitetime_high": 16.0}}, "29717": {"36397": {"catches": "64", "naive": 0, "uniform": 0, "kde": 0, "bitetime_low": 8.5, "bitetime_high": 18.0}, "36412": {"catches": "57", "naive": 0, "uniform": 0, "kde": 0, "bitetime_low": 10.5, "bitetime_high": 24.5}}}}