{"bait": {"2585": {"name": "Lugworm", "misses": 0, "total": 60}, "4869": {"name": "Merlthor Goby", "misses": 0, "total": 189}, "4872": {"name": "Ocean Cloud", "misses": 273, "total": 881}, "2587": {"name": "Pill Bug", "misses": 0, "total": 1375}, "2596": {"name": "Spoon Worm", "misses": 0, "total": 179}, "29717": {"name": "Versatile Lure", "misses": 0, "total": 92}, "4904": {"name": "Wahoo", "misses": 0, "total": 66}, "2628": {"name": "Yumizuno", "misses": 0, "total": 86}}, "fish": {"4872": {"name": "Ocean Cloud", "tug": "1"}, "4869": {"name": "Merlthor Goby", "tug": "1"}, "4921": {"name": "Sunfish", "tug": "2"}, "4904": {"name": "Wahoo", "tug": "2"}, "4903": {"name": "Silver Shark", "tug": "2"}, "7941": {"name": "Helmsman's Hand", "tug": "3"}, "4907": {"name": "Pike Eel", "tug": "2"}, "4898": {"name": "Fullmoon Sardine", "tug": "1"}}, "rates": {"2585": {"4869": {"catches": "60", "naive": 0, "uniform": 0, "kde": 0, "bitetime_low": 7.5, "bitetime_high": 18.5}}, "4869": {"4903": {"catches": "69", "naive": 0, "uniform": 0, "kde": 0, "bitetime_low": 13.0, "bitetime_high": 21.5}, "4904": {"catches": "120", "naive": 0, "uniform": 0, "kde": 0, "bitetime_low": 9.5, "bitetime_high": 16.5}}, "4872": {"7941": {"catches": "77", "naive": 7, "uniform": 7, "kde": 7, "bitetime_low": 30.5, "bitetime_high": 59.0}, "4921": {"catches": "531", "naive": 266, "uniform": 266, "kde": 266, "bitetime_low": 14.5, "bitetime_high": 31.0}}, "2587": {"4869": {"catches": "395", "naive": 0, "uniform": 0, "kde": 0, "bitetime_low": 12.5, "bitetime_high": 19.5}, "4872": {"catches": "980", "naive": 0, "uniform": 0, "kde": 0, "bitetime_low": 12.5, "bitetime_high": 22.5}}, "2596": {"4898": {"catches": "128", "naive": 0, "uniform": 0, "kde": 0, "bitetime_low": 6.5, "bitetime_high": 13.5}, "4869": {"catches": "51", "naive": 0, "uniform": 0, "kde": 0, "bitetime_low": 12.5, "bitetime_high": 19.5}}, "29717": {"4869": {"catches": "47", "naive": 0, "uniform": 0, "kde": 0, "bitetime_low": 12.0, "bitetime_high": 18.0}, "4872": {"catches": "45", "naive": 0, "uniform": 0, "kde": 0, "bitetime_low": 14.5, "bitetime_high": 25.0}}, "4904": {"4903": {"catches": "66", "naive": 0, "uniform": 0, "kde": 0, "bitetime_low": 11.0, "bitetime_high": 23.5}}, "2628": {"4907": {"catches": "86", "naive": 0, "uniform": 0, "kde": 0, "bitetime_low": 9.5, "bitetime_high": 20.0}}}}